logging_color/__init__.py
logging_color-0.1.2.dist-info/LICENSE
logging_color-0.1.2.dist-info/METADATA
logging_color-0.1.2.dist-info/WHEEL
logging_color-0.1.2.dist-info/top_level.txt
logging_color-0.1.2.dist-info/RECORD
